setup.py
newToolsNew.egg-info/PKG-INFO
newToolsNew.egg-info/SOURCES.txt
newToolsNew.egg-info/dependency_links.txt
newToolsNew.egg-info/entry_points.txt
newToolsNew.egg-info/requires.txt
newToolsNew.egg-info/top_level.txt
newUtils/logger.py