Metadata-Version: 2.1
Name: newToolsNew
Version: 2024.0.0.8
Summary: More convenient to create tools project
Home-page: http://git.ppdaicorp.com/pengying/tools_py.git
Author: py_new
Author-email: pengying@ppdai.com
License: MIT
Platform: UNKNOWN
